setup.py
singularity_a_distributions/Binomialdistribution.py
singularity_a_distributions/Gaussiandistribution.py
singularity_a_distributions/Generaldistribution.py
singularity_a_distributions/__init__.py
singularity_a_distributions.egg-info/PKG-INFO
singularity_a_distributions.egg-info/SOURCES.txt
singularity_a_distributions.egg-info/dependency_links.txt
singularity_a_distributions.egg-info/not-zip-safe
singularity_a_distributions.egg-info/top_level.txt