Metadata-Version: 2.1
Name: singularity-a-distributions
Version: 1.0
Summary: Gaussian distributions
Author: Abdullah Hammami
